LICENSE.md
README.md
pyproject.toml
tests/test_lattice.py
tmdybinding/__init__.py
tmdybinding/tmd_abstract_lattice.py
tmdybinding/tmd_hopping_matrices.py
tmdybinding/tmd_lattice.py
tmdybinding.egg-info/PKG-INFO
tmdybinding.egg-info/SOURCES.txt
tmdybinding.egg-info/dependency_links.txt
tmdybinding.egg-info/requires.txt
tmdybinding.egg-info/top_level.txt
tmdybinding/parameters/__init__.py
tmdybinding/parameters/slater_koster.py
tmdybinding/parameters/symmetry_group.py