Metadata-Version: 2.1
Name: tmdybinding
Version: 0.1.2
Summary: Tight-binding lattices for TMDs for the Pybinding-package, Documentation: https://bertjorissen.github.io/tmdybinding (c) 2022-2024
Author-email: Bert Jorissen <info@bertjorissen.be>
License: Attribution 4.0 International
Project-URL: repository, https://github.com/BertJorissen/tmdybinding
Project-URL: documentation, https://bertjorissen.github.io/tmdybinding
Project-URL: changelog, https://github.com/BertJorissen/tmdybinding/blob/master/changelog.md
Keywords: pybinding,tight-binding,solid-state physics,physics,cmt,quantum,graphene,TMD,KPM,CPGF
Classifier: Development Status :: 5 - Production/Stable
Classifier: Intended Audience :: Science/Research
Classifier: Topic :: Scientific/Engineering :: Physics
Classifier: Programming Language :: Python :: 3 :: Only
Classifier: Programming Language :: Python :: 3.9
Classifier: Programming Language :: Python :: 3.10
Classifier: Programming Language :: Python :: 3.11
Classifier: Programming Language :: Python :: 3.12
Requires-Python: >=3.9
License-File: LICENSE.md
Requires-Dist: pybinding-dev>=0.9
